chromedriver_auto/__init__.py
chromedriver_auto/driver_ready.py
chromedriver_auto/test.py
chromedriver_auto-1.0.12.dist-info/LICENSE
chromedriver_auto-1.0.12.dist-info/METADATA
chromedriver_auto-1.0.12.dist-info/WHEEL
chromedriver_auto-1.0.12.dist-info/top_level.txt
chromedriver_auto-1.0.12.dist-info/RECORD
